LICENSE
README.rst
overrides_extension/__init__.py
overrides_extension/enforce.py
overrides_extension/final.py
overrides_extension/override.py
tests/test_decorator_params.py
tests/test_enforce.py
tests/test_final.py
tests/test_override.py
tests/test_somefinalpackage.py
tests/test_somepackage.py
tox.ini
overrides_extension-3.2.3.dist-info/LICENSE
overrides_extension-3.2.3.dist-info/WHEEL
overrides_extension-3.2.3.dist-info/METADATA
overrides_extension-3.2.3.dist-info/RECORD
