Metadata-Version: 2.1
Name: overrides-extension
Version: 3.2.3
Summary: A decorator to automatically detect mismatch when overriding a method.
Home-page: https://github.com/mozharovsky/overrides
License: Apache License, Version 2.0
Keywords: override,inheritence,OOP
Author: Mikko Korpela
Author-email: mikko.korpela@gmail.com
Requires-Python: >=3.6.0,<3.10.0
Classifier: Intended Audience :: Developers
Classifier: License :: Other/Proprietary License
Classifier: Natural Language :: English
Classifier: Programming Language :: Python :: 3
Classifier: Programming Language :: Python :: 3.6
Classifier: Programming Language :: Python :: 3.7
Classifier: Programming Language :: Python :: 3.8
Classifier: Programming Language :: Python :: 3.9
Project-URL: Repository, https://github.com/mozharovsky/overrides
